ndi_ptz/__init__.py
ndi_ptz/_pygame.py
ndi_ptz/cli.py
ndi_ptz/constants.py
ndi_ptz/joysticks.py
ndi_ptz-0.1.5.dist-info/METADATA
ndi_ptz-0.1.5.dist-info/WHEEL
ndi_ptz-0.1.5.dist-info/entry_points.txt
ndi_ptz-0.1.5.dist-info/licenses/LICENSE
ndi_ptz-0.1.5.dist-info/RECORD
