Metadata-Version: 2.4
Name: ndi-ptz
Version: 0.1.5
Summary: A CLI to control NDI-capable PTZ cameras via a joystick.
License-Expression: MIT
License-File: LICENSE
Keywords: joystick,ndi,obs,ptz,streaming,video
Requires-Python: >=3.12
Requires-Dist: click>=8.2.1
Requires-Dist: cyndilib>=0.0.7
Requires-Dist: pygame>=2.6.1
